l1log-0.3.2.dist-info/licenses/LICENSE
thonnycontrib/__init__.py
thonnycontrib/l1log_utils.py
thonnycontrib/thonny-LoggingPlugin.py
thonnycontrib/thonny_LoggingPlugin/__init__.py
thonnycontrib/thonny_LoggingPlugin/mainApp.py
thonnycontrib/thonny_LoggingPlugin/communication/__init__.py
thonnycontrib/thonny_LoggingPlugin/communication/sendingClient.py
thonnycontrib/thonny_LoggingPlugin/configuration/__init__.py
thonnycontrib/thonny_LoggingPlugin/configuration/configBinome.py
thonnycontrib/thonny_LoggingPlugin/configuration/configXApi.py
thonnycontrib/thonny_LoggingPlugin/configuration/configuration.py
thonnycontrib/thonny_LoggingPlugin/configuration/globals.py
thonnycontrib/thonny_LoggingPlugin/event/event.py
thonnycontrib/thonny_LoggingPlugin/event/eventFactory.py
thonnycontrib/thonny_LoggingPlugin/event/eventManager.py
thonnycontrib/thonny_LoggingPlugin/event/event_endSession.py
thonnycontrib/thonny_LoggingPlugin/event/event_l1Tests.py
thonnycontrib/thonny_LoggingPlugin/event/event_l1TestsDocGenerator.py
thonnycontrib/thonny_LoggingPlugin/event/event_notReferenced.py
thonnycontrib/thonny_LoggingPlugin/event/event_open.py
thonnycontrib/thonny_LoggingPlugin/event/event_save.py
thonnycontrib/thonny_LoggingPlugin/event/event_shellCommand.py
thonnycontrib/thonny_LoggingPlugin/event/event_shellDebugger.py
thonnycontrib/thonny_LoggingPlugin/event/event_shellProgram.py
thonnycontrib/thonny_LoggingPlugin/event/event_startSession.py
thonnycontrib/thonny_LoggingPlugin/formats/__init__.py
thonnycontrib/thonny_LoggingPlugin/formats/xAPI_creation.py
thonnycontrib/thonny_LoggingPlugin/popups/l1log_popups.py
thonnycontrib/thonny_LoggingPlugin/popups/ldap_connection.py
thonnycontrib/thonny_LoggingPlugin/processing/__init__.py
thonnycontrib/thonny_LoggingPlugin/processing/formatData.py
l1log-0.3.2.dist-info/METADATA
l1log-0.3.2.dist-info/WHEEL
l1log-0.3.2.dist-info/top_level.txt
l1log-0.3.2.dist-info/RECORD
