Metadata-Version: 2.4
Name: L1log
Version: 0.3.2
Summary: A plugin for Thonny that logs and sends all the user's actions to an LRS
Home-page: https://gitlab.univ-lille.fr/mirabelle.nebut/thonny-logs
Author: Corentin DUVIVIER, Thomas BRICHE
Author-email: Mirabelle NEBUT <mirabelle.nebut@univ-lille.fr>, Yvan PETER <yvan.peter@univ-lille.fr>
License: Copyright (c) 2018 The Python Packaging Authority
Platform: Windows
Platform: macOS
Platform: Linux
Classifier: Programming Language :: Python :: 3
Classifier: License :: OSI Approved :: MIT License
Classifier: Operating System :: OS Independent
Classifier: Development Status :: 3 - Alpha
Classifier: Topic :: Education
Classifier: Intended Audience :: Education
Classifier: Intended Audience :: Developers
Requires-Python: >=3.10
License-File: LICENSE
Requires-Dist: thonny>=4.0.0
Requires-Dist: requests
Requires-Dist: python-ldap
Dynamic: home-page
Dynamic: license-file
Dynamic: platform
Dynamic: requires-python
